LICENSE.txt
README.md
setup.cfg
setup.py
get_nse_daily.egg-info/PKG-INFO
get_nse_daily.egg-info/SOURCES.txt
get_nse_daily.egg-info/dependency_links.txt
get_nse_daily.egg-info/requires.txt
get_nse_daily.egg-info/top_level.txt
nse_daily/__init__.py
nse_daily/bse/__init__.py
nse_daily/common/__init__.py
nse_daily/nse/__init__.py