Metadata-Version: 2.1
Name: get-nse-daily
Version: 0.3
Summary: pure python library built using requests to get daily day end data from nse india
Home-page: https://github.com/v33rh0ra/get_nse_daily
Author: Tanveer Hora
Author-email: tanveer.hora@gmail.com
License: MIT
Download-URL: https://github.com/v33rh0ra/get_nse_daily/archive/v_03.tar.gz
Project-URL: Documentation, https://v33rh0ra.github.io/get_nse_daily/nse_daily/index.html
Project-URL: Bug Tracker, https://github.com/v33rh0ra/get_nse_daily/issues
Project-URL: Source Code, https://github.com/v33rh0ra/get_nse_daily
Keywords: nse,bhavcopy,bhav
Platform: UNKNOWN
Classifier: Operating System :: OS Independent
Classifier: Programming Language :: Python :: 3
Classifier: Programming Language :: Python :: 3.7
Classifier: Topic :: Scientific/Engineering
Classifier: License :: OSI Approved :: MIT License
Classifier: Development Status :: 3 - Alpha
Classifier: Environment :: Console
Classifier: Intended Audience :: Developers
License-File: LICENSE.txt
